vce/__init__.py
vce/__main__.py
vce/agent.py
vce/cloud.py
vce/db.py
vce/orbits.py
vce/server.py
vce/utils.py
vce/templates/stack.yml.j2
vce-0.1.0.dist-info/LICENSE
vce-0.1.0.dist-info/METADATA
vce-0.1.0.dist-info/WHEEL
vce-0.1.0.dist-info/entry_points.txt
vce-0.1.0.dist-info/top_level.txt
vce-0.1.0.dist-info/RECORD
