Metadata-Version: 2.1
Name: vce
Version: 0.1.0
Summary: Virtual Constellation Engine.
Home-page: http://www.isi.edu
Author: Marco Paolieri
Author-email: paolieri@usc.edu
License: AGPLv3
Platform: UNKNOWN
Classifier: License :: OSI Approved :: GNU Affero General Public License v3
Classifier: Programming Language :: Python
Classifier: Programming Language :: Python :: 3.7
Classifier: Programming Language :: Python :: Implementation :: CPython
Requires-Dist: Cartopy
Requires-Dist: click
Requires-Dist: influxdb
Requires-Dist: jinja2
Requires-Dist: matplotlib
Requires-Dist: netifaces
Requires-Dist: pyqt5
Requires-Dist: requests
Requires-Dist: responder
Requires-Dist: scipy
Requires-Dist: strictyaml
Requires-Dist: tcconfig
